{
  "batch_meta": {
    "batch_id": "2001-11-evt-20260111-001",
    "generated_utc": "2026-01-11T00:00:00Z",
    "mode": "historical_month",
    "time_window_days": null,
    "target_month": "2001-11",
    "window": {
      "start_utc": "2001-11-01T00:00:00.000Z",
      "end_utc": "2001-11-30T23:59:59.000Z"
    },
    "categories_requested": [
      "pollution_contamination",
      "weather_climate",
      "geological",
      "fires",
      "ecosystem_biodiversity",
      "policy_regulation"
    ],
    "agent": {
      "name": "gaialog-json-normalizer",
      "version": "1.0",
      "model": "unknown",
      "retrieval_method": "curated"
    }
  },
  "events": [
    {
      "event_id": "evt-2001-11-27-galax-va-cwa-lawsuit",
      "title": "DOJ/EPA files Clean Water Act lawsuit against City of Galax, Virginia over sewage overflows",
      "description": "The U.S. Department of Justice, on behalf of EPA, filed a Clean Water Act lawsuit against the City of Galax, alleging permit violations at its wastewater and drinking water treatment plants. The complaint alleged longstanding sewage overflows and discharges to nearby waterways.",
      "category_primary": "pollution_contamination",
      "polarity": "negative",
      "severity": null,
      "time": {
        "event_start": null,
        "event_end": null,
        "reported_at": "2001-11-27T00:00:00.000Z",
        "time_confidence": 0.75,
        "event_date_utc": "2001-11-27T00:00:00.000Z",
        "event_date_precision": "day"
      },
      "location": {
        "name": "Galax, Virginia, USA",
        "jurisdiction_level": "city",
        "admin1": "Virginia",
        "country": "US",
        "capital_used": null,
        "lat": 36.6612,
        "lon": -80.9237,
        "precision": "city",
        "location_basis": "explicit_in_article",
        "location_confidence": 0.7
      },
      "sources": [
        {
          "url": "https://www.epa.gov/archive/epapages/newsroom_archive/newsreleases/a017ef9d385d839e852570d60070fcc7.html",
          "source_name": "U.S. Environmental Protection Agency (archive)",
          "published_at": "2001-11-27T00:00:00.000Z",
          "headline": "U.S. Files Clean Water Act Suit Against City Of Galax, Virginia",
          "byline": null,
          "accessed_utc": "2026-01-11T00:00:00Z",
          "canonical_url": null
        }
      ],
      "entities": {
        "organizations": [
          "U.S. Department of Justice",
          "U.S. Environmental Protection Agency (EPA)",
          "City of Galax"
        ],
        "substances": [],
        "ecosystems": [
          "Chestnut Creek",
          "Oglesby Branch",
          "New River"
        ],
        "people": []
      },
      "evidence": {
        "key_quotes": [
          {
            "quote": "The U.S. Department of Justice filed a Clean Water Act lawsuit against the City of Galax, Va.",
            "source_url": "https://www.epa.gov/archive/epapages/newsroom_archive/newsreleases/a017ef9d385d839e852570d60070fcc7.html"
          }
        ]
      },
      "confidence": {
        "overall": 0.72,
        "category": 0.85,
        "location": 0.7,
        "summary_grounding": 0.75
      },
      "quality_flags": [
        "date_ambiguous",
        "location_ambiguous"
      ],
      "dedupe": {
        "cluster_hint": "epa-doj-cwa-galax-va-sewage-overflows-2001-11-27",
        "fingerprint": "cwa_lawsuit_galax_virginia_2001-11-27"
      }
    },
    {
      "event_id": "evt-2001-11-01-illinois-river-lasalle-hydraulic-oil",
      "title": "Hydraulic oil release reported to Illinois River near LaSalle County Nuclear Station intake structure",
      "description": "An NRC event notification reported a hydraulic fluid leak at the river intake structure associated with LaSalle County Nuclear Station. The notification described a small release of oil to the Illinois River and reporting to relevant response authorities.",
      "category_primary": "pollution_contamination",
      "polarity": "negative",
      "severity": null,
      "time": {
        "event_start": null,
        "event_end": null,
        "reported_at": "2001-11-01T00:00:00.000Z",
        "time_confidence": 0.6,
        "event_date_utc": "2001-11-01T00:00:00.000Z",
        "event_date_precision": "day"
      },
      "location": {
        "name": "Illinois River near LaSalle County Nuclear Station, Illinois, USA",
        "jurisdiction_level": "site",
        "admin1": "Illinois",
        "country": "US",
        "capital_used": null,
        "lat": 41.2406,
        "lon": -88.6695,
        "precision": "admin1",
        "location_basis": "explicit_in_article",
        "location_confidence": 0.45
      },
      "sources": [
        {
          "url": "https://www.nrc.gov/reading-rm/doc-collections/event-status/event/2001/20011101en.html",
          "source_name": "U.S. Nuclear Regulatory Commission (NRC)",
          "published_at": "2001-11-01T00:00:00.000Z",
          "headline": "Event Notifications (Nov 1, 2001)",
          "byline": null,
          "accessed_utc": "2026-01-11T00:00:00Z",
          "canonical_url": null
        }
      ],
      "entities": {
        "organizations": [
          "U.S. Nuclear Regulatory Commission (NRC)",
          "National Response Center",
          "Illinois Emergency Management Agency"
        ],
        "substances": [
          "hydraulic oil"
        ],
        "ecosystems": [
          "Illinois River"
        ],
        "people": []
      },
      "evidence": {
        "key_quotes": [
          {
            "quote": "hydraulic fluid leak ... release of oil to the Illinois River",
            "source_url": "https://www.nrc.gov/reading-rm/doc-collections/event-status/event/2001/20011101en.html"
          }
        ]
      },
      "confidence": {
        "overall": 0.48,
        "category": 0.7,
        "location": 0.4,
        "summary_grounding": 0.55
      },
      "quality_flags": [
        "location_ambiguous",
        "date_ambiguous"
      ],
      "dedupe": {
        "cluster_hint": "nrc-event-illinois-river-lasalle-hydraulic-oil-2001-11-01",
        "fingerprint": "nrc_hydraulic_oil_illinois_river_2001-11-01"
      }
    },
    {
      "event_id": "evt-2001-11-06-atlantic-canada-coastal-storm",
      "title": "Major coastal storm impacts Atlantic Canada in early November 2001",
      "description": "Environment and Climate Change Canada’s 2001 season summary describes a powerful storm affecting Atlantic Canada in early November 2001. The event brought strong winds and marine impacts, contributing to widespread power outages and coastal effects in the region.",
      "category_primary": "weather_climate",
      "polarity": "negative",
      "severity": null,
      "time": {
        "event_start": null,
        "event_end": null,
        "reported_at": "2001-11-30T00:00:00.000Z",
        "time_confidence": 0.45,
        "event_date_utc": null,
        "event_date_precision": "range_anchor"
      },
      "location": {
        "name": "Atlantic Canada (Nova Scotia, New Brunswick, Prince Edward Island, Newfoundland and Labrador)",
        "jurisdiction_level": "supranational",
        "admin1": null,
        "country": null,
        "capital_used": "Ottawa",
        "lat": 45.4215,
        "lon": -75.6972,
        "precision": "proxy",
        "location_basis": "capital_rule",
        "location_confidence": 0.35
      },
      "sources": [
        {
          "url": "https://www.canada.ca/en/environment-climate-change/services/archive/hurricanes/canadian-tropical-cyclone-season-summaries-2000s/2001.html",
          "source_name": "Government of Canada (Environment and Climate Change Canada)",
          "published_at": "2001-11-30T00:00:00.000Z",
          "headline": "Canadian Tropical Cyclone Season Summary: 2001",
          "byline": null,
          "accessed_utc": "2026-01-11T00:00:00Z",
          "canonical_url": null
        }
      ],
      "entities": {
        "organizations": [
          "Environment and Climate Change Canada"
        ],
        "substances": [],
        "ecosystems": [
          "Northwest Atlantic (marine/coastal)"
        ],
        "people": []
      },
      "evidence": {
        "key_quotes": [
          {
            "quote": "a powerful fall storm affected Atlantic Canada",
            "source_url": "https://www.canada.ca/en/environment-climate-change/services/archive/hurricanes/canadian-tropical-cyclone-season-summaries-2000s/2001.html"
          }
        ]
      },
      "confidence": {
        "overall": 0.4,
        "category": 0.6,
        "location": 0.35,
        "summary_grounding": 0.45
      },
      "quality_flags": [
        "date_ambiguous",
        "location_ambiguous",
        "secondary_sources_only"
      ],
      "dedupe": {
        "cluster_hint": "atlantic-canada-storm-early-nov-2001",
        "fingerprint": "atlantic_canada_storm_2001-11"
      }
    },
    {
      "event_id": "evt-2001-11-14-kunlun-earthquake-qinghai",
      "title": "Mw 7.8 Kunlun (Kokoxili) earthquake strikes northern Tibetan Plateau, China",
      "description": "A major strike-slip earthquake occurred on the Kunlun fault system in November 2001, as described in a USGS publication comparing the Kunlun and Denali earthquakes. The event produced extensive surface rupture in a remote part of the northern Tibetan Plateau.",
      "category_primary": "geological",
      "polarity": "negative",
      "severity": null,
      "time": {
        "event_start": "2001-11-14T09:26:10.000Z",
        "event_end": null,
        "reported_at": "2001-11-14T09:26:10.000Z",
        "time_confidence": 0.65,
        "event_date_utc": "2001-11-14T09:26:10.000Z",
        "event_date_precision": "exact"
      },
      "location": {
        "name": "Qinghai Province, China (Kunlun fault/Kokoxili region)",
        "jurisdiction_level": "state",
        "admin1": "Qinghai",
        "country": "CN",
        "capital_used": "Xining",
        "lat": 36.6171,
        "lon": 101.7782,
        "precision": "admin1",
        "location_basis": "capital_rule",
        "location_confidence": 0.5
      },
      "sources": [
        {
          "url": "https://www.usgs.gov/publications/comparing-november-2002-denali-and-november-2001-kunlun-earthquakes",
          "source_name": "U.S. Geological Survey (USGS)",
          "published_at": "2002-01-01T00:00:00.000Z",
          "headline": "Comparing the November 2002 Denali and November 2001 Kunlun earthquakes",
          "byline": null,
          "accessed_utc": "2026-01-11T00:00:00Z",
          "canonical_url": null
        }
      ],
      "entities": {
        "organizations": [
          "U.S. Geological Survey (USGS)"
        ],
        "substances": [],
        "ecosystems": [
          "Kunlun fault zone"
        ],
        "people": []
      },
      "evidence": {
        "key_quotes": [
          {
            "quote": "November 2001 Kunlun earthquakes",
            "source_url": "https://www.usgs.gov/publications/comparing-november-2002-denali-and-november-2001-kunlun-earthquakes"
          }
        ]
      },
      "confidence": {
        "overall": 0.55,
        "category": 0.75,
        "location": 0.5,
        "summary_grounding": 0.55
      },
      "quality_flags": [
        "date_ambiguous",
        "location_ambiguous",
        "secondary_sources_only"
      ],
      "dedupe": {
        "cluster_hint": "kunlun-earthquake-2001-11-14-qinghai",
        "fingerprint": "kunlun_eq_qinghai_2001-11-14"
      }
    },
    {
      "event_id": "evt-2001-11-10-marrakesh-accords-cop7",
      "title": "COP7 adopts the Marrakesh Accords to implement key elements of the Kyoto Protocol",
      "description": "At UNFCCC COP7 in Marrakech, Parties agreed to the Marrakesh Accords, a package of decisions setting out detailed rules and mechanisms for implementing the Kyoto Protocol. The Accords addressed areas such as accounting, reporting/review, and support arrangements.",
      "category_primary": "policy_regulation",
      "polarity": "positive",
      "severity": null,
      "time": {
        "event_start": null,
        "event_end": null,
        "reported_at": "2001-11-10T00:00:00.000Z",
        "time_confidence": 0.5,
        "event_date_utc": "2001-11-10T00:00:00.000Z",
        "event_date_precision": "day"
      },
      "location": {
        "name": "Marrakech, Morocco",
        "jurisdiction_level": "city",
        "admin1": null,
        "country": "MA",
        "capital_used": null,
        "lat": 31.6295,
        "lon": -7.9811,
        "precision": "city",
        "location_basis": "explicit_in_article",
        "location_confidence": 0.6
      },
      "sources": [
        {
          "url": "https://unfccc.int/process-and-meetings/transparency-and-reporting/reporting-and-review-under-the-kyoto-protocol/overview/background-and-resources/the-guidelines-to-implement-the-kyoto-protocol-the-marrakesh-accords-and-the-578-implications",
          "source_name": "UNFCCC",
          "published_at": "2001-11-10T00:00:00.000Z",
          "headline": "The guidelines to implement the Kyoto Protocol: the Marrakesh Accords and the 5/CP.8 implications",
          "byline": null,
          "accessed_utc": "2026-01-11T00:00:00Z",
          "canonical_url": null
        },
        {
          "url": "https://www.nrdc.org/press-releases/marrakech-agreement-clears-last-hurdle-global-warming-treaty",
          "source_name": "NRDC",
          "published_at": "2001-11-10T00:00:00.000Z",
          "headline": "Marrakech Agreement Clears Last Hurdle for Global Warming Treaty",
          "byline": null,
          "accessed_utc": "2026-01-11T00:00:00Z",
          "canonical_url": null
        }
      ],
      "entities": {
        "organizations": [
          "UNFCCC"
        ],
        "substances": [],
        "ecosystems": [],
        "people": []
      },
      "evidence": {
        "key_quotes": [
          {
            "quote": "the Marrakesh Accords",
            "source_url": "https://unfccc.int/process-and-meetings/transparency-and-reporting/reporting-and-review-under-the-kyoto-protocol/overview/background-and-resources/the-guidelines-to-implement-the-kyoto-protocol-the-marrakesh-accords-and-the-578-implications"
          }
        ]
      },
      "confidence": {
        "overall": 0.58,
        "category": 0.7,
        "location": 0.6,
        "summary_grounding": 0.55
      },
      "quality_flags": [
        "date_ambiguous",
        "possible_opinion_or_advocacy"
      ],
      "dedupe": {
        "cluster_hint": "unfccc-cop7-marrakesh-accords-2001-11",
        "fingerprint": "marrakesh_accords_marrakech_2001-11"
      }
    },
    {
      "event_id": "evt-2001-11-09-epa-316b-new-facilities-final-rule",
      "title": "EPA issues final Clean Water Act §316(b) standards for cooling-water intake structures at new facilities",
      "description": "EPA announced a final rule setting standards for cooling-water intake structures at new facilities under Clean Water Act §316(b). The standards were intended to reduce adverse environmental impacts such as fish and shellfish kills.",
      "category_primary": "policy_regulation",
      "polarity": "positive",
      "severity": null,
      "time": {
        "event_start": null,
        "event_end": null,
        "reported_at": "2001-11-09T00:00:00.000Z",
        "time_confidence": 0.75,
        "event_date_utc": "2001-11-09T00:00:00.000Z",
        "event_date_precision": "day"
      },
      "location": {
        "name": "United States (federal rulemaking)",
        "jurisdiction_level": "country",
        "admin1": null,
        "country": "US",
        "capital_used": "Washington, DC",
        "lat": 38.9072,
        "lon": -77.0369,
        "precision": "country",
        "location_basis": "capital_rule",
        "location_confidence": 0.7
      },
      "sources": [
        {
          "url": "https://www.epa.gov/archive/epapages/newsroom_archive/newsreleases/cd5f73e9041eeb4b85256aff007a067f.html",
          "source_name": "U.S. Environmental Protection Agency (archive)",
          "published_at": "2001-11-09T00:00:00.000Z",
          "headline": "EPA Issues Final Rules to Protect Fish and Shellfish from Cooling Water Intake Structures at New Facilities",
          "byline": null,
          "accessed_utc": "2026-01-11T00:00:00Z",
          "canonical_url": null
        }
      ],
      "entities": {
        "organizations": [
          "U.S. Environmental Protection Agency (EPA)"
        ],
        "substances": [],
        "ecosystems": [],
        "people": []
      },
      "evidence": {
        "key_quotes": [
          {
            "quote": "EPA ... issued final regulations ... cooling water intake structures at new facilities",
            "source_url": "https://www.epa.gov/archive/epapages/newsroom_archive/newsreleases/cd5f73e9041eeb4b85256aff007a067f.html"
          }
        ]
      },
      "confidence": {
        "overall": 0.7,
        "category": 0.8,
        "location": 0.7,
        "summary_grounding": 0.75
      },
      "quality_flags": [
        "date_ambiguous"
      ],
      "dedupe": {
        "cluster_hint": "epa-316b-cooling-water-intake-new-facilities-2001-11-09",
        "fingerprint": "epa_316b_new_facilities_2001-11-09"
      }
    },
    {
      "event_id": "evt-2001-11-13-baton-rouge-sewer-overflow-consent-decree",
      "title": "Consent decree announced to reduce sewage overflows in Baton Rouge / East Baton Rouge Parish, Louisiana",
      "description": "The United States and the State of Louisiana announced a settlement to address alleged Clean Water Act violations involving the wastewater collection and treatment system serving Baton Rouge and East Baton Rouge Parish. The settlement required infrastructure improvements intended to reduce discharges of untreated sewage.",
      "category_primary": "policy_regulation",
      "polarity": "positive",
      "severity": null,
      "time": {
        "event_start": null,
        "event_end": null,
        "reported_at": "2001-11-13T00:00:00.000Z",
        "time_confidence": 0.8,
        "event_date_utc": "2001-11-13T00:00:00.000Z",
        "event_date_precision": "day"
      },
      "location": {
        "name": "Baton Rouge, Louisiana, USA",
        "jurisdiction_level": "city",
        "admin1": "Louisiana",
        "country": "US",
        "capital_used": null,
        "lat": 30.4515,
        "lon": -91.1871,
        "precision": "city",
        "location_basis": "explicit_in_article",
        "location_confidence": 0.7
      },
      "sources": [
        {
          "url": "https://www.epa.gov/archive/epapages/newsroom_archive/newsreleases/fc0fc49a6a0cc32f85256b040058af04.html",
          "source_name": "U.S. Environmental Protection Agency (archive)",
          "published_at": "2001-11-13T00:00:00.000Z",
          "headline": "United States And Louisiana Announce Settlement To Address Sewage Overflows In Baton Rouge, Louisiana Area",
          "byline": null,
          "accessed_utc": "2026-01-11T00:00:00Z",
          "canonical_url": null
        },
        {
          "url": "https://www.epa.gov/enforcement/city-baton-rouge-and-east-baton-rough-parish-louisiana-sewer-overflow-settlement",
          "source_name": "U.S. Environmental Protection Agency (Enforcement)",
          "published_at": "2001-11-13T00:00:00.000Z",
          "headline": "City of Baton Rouge and East Baton Rouge Parish, Louisiana Sewer Overflow Settlement",
          "byline": null,
          "accessed_utc": "2026-01-11T00:00:00Z",
          "canonical_url": null
        }
      ],
      "entities": {
        "organizations": [
          "U.S. Environmental Protection Agency (EPA)",
          "U.S. Department of Justice",
          "State of Louisiana",
          "City of Baton Rouge",
          "East Baton Rouge Parish"
        ],
        "substances": [
          "sewage"
        ],
        "ecosystems": [],
        "people": []
      },
      "evidence": {
        "key_quotes": [
          {
            "quote": "announce settlement to address sewage overflows in Baton Rouge, Louisiana area",
            "source_url": "https://www.epa.gov/archive/epapages/newsroom_archive/newsreleases/fc0fc49a6a0cc32f85256b040058af04.html"
          }
        ]
      },
      "confidence": {
        "overall": 0.73,
        "category": 0.8,
        "location": 0.7,
        "summary_grounding": 0.75
      },
      "quality_flags": [
        "date_ambiguous"
      ],
      "dedupe": {
        "cluster_hint": "baton-rouge-east-baton-rouge-sewer-overflow-settlement-2001-11-13",
        "fingerprint": "baton_rouge_sewer_settlement_2001-11-13"
      }
    },
    {
      "event_id": "evt-2001-11-13-monongahela-power-oil-spill-settlement",
      "title": "Settlement announced with Monongahela Power (Allegheny Power) over oil-spill prevention following transformer incident",
      "description": "EPA and DOJ announced a settlement with Monongahela Power Company (doing business as Allegheny Power) requiring penalties and measures intended to prevent future oil spills. The settlement related to an earlier transformer incident and oil spill that affected nearby waterways in West Virginia.",
      "category_primary": "policy_regulation",
      "polarity": "positive",
      "severity": null,
      "time": {
        "event_start": null,
        "event_end": null,
        "reported_at": "2001-11-13T00:00:00.000Z",
        "time_confidence": 0.75,
        "event_date_utc": "2001-11-13T00:00:00.000Z",
        "event_date_precision": "day"
      },
      "location": {
        "name": "Willow Island, West Virginia, USA",
        "jurisdiction_level": "city",
        "admin1": "West Virginia",
        "country": "US",
        "capital_used": null,
        "lat": 39.3476,
        "lon": -81.3562,
        "precision": "city",
        "location_basis": "explicit_in_article",
        "location_confidence": 0.55
      },
      "sources": [
        {
          "url": "https://www.epa.gov/archive/epapages/newsroom_archive/newsreleases/530b451954bb8b98852570d60070fccb.html",
          "source_name": "U.S. Environmental Protection Agency (archive)",
          "published_at": "2001-11-13T00:00:00.000Z",
          "headline": "Monongahela Power Company And U.S. Reach Settlement To Prevent Oil Spills In West Virginia",
          "byline": null,
          "accessed_utc": "2026-01-11T00:00:00Z",
          "canonical_url": null
        },
        {
          "url": "https://www.epa.gov/enforcement/monongahela-power-company-dba-allegheny-power-company-oil-spills-settlement",
          "source_name": "U.S. Environmental Protection Agency (Enforcement)",
          "published_at": "2001-11-13T00:00:00.000Z",
          "headline": "Monongahela Power Company (d/b/a Allegheny Power Company) Oil Spills Settlement",
          "byline": null,
          "accessed_utc": "2026-01-11T00:00:00Z",
          "canonical_url": null
        },
        {
          "url": "https://www.epa.gov/enforcement/consent-decree-monongahela-power-company-dba-allegheny-power-company-oil-spills",
          "source_name": "U.S. Environmental Protection Agency (Enforcement)",
          "published_at": "2001-11-13T00:00:00.000Z",
          "headline": "Consent Decree: Monongahela Power Company (d/b/a Allegheny Power Company) Oil Spills",
          "byline": null,
          "accessed_utc": "2026-01-11T00:00:00Z",
          "canonical_url": null
        }
      ],
      "entities": {
        "organizations": [
          "U.S. Environmental Protection Agency (EPA)",
          "U.S. Department of Justice",
          "Monongahela Power Company",
          "Allegheny Power"
        ],
        "substances": [
          "transformer oil"
        ],
        "ecosystems": [
          "Cow Creek"
        ],
        "people": []
      },
      "evidence": {
        "key_quotes": [
          {
            "quote": "reach settlement to prevent oil spills in West Virginia",
            "source_url": "https://www.epa.gov/archive/epapages/newsroom_archive/newsreleases/530b451954bb8b98852570d60070fccb.html"
          }
        ]
      },
      "confidence": {
        "overall": 0.68,
        "category": 0.8,
        "location": 0.55,
        "summary_grounding": 0.7
      },
      "quality_flags": [
        "date_ambiguous",
        "location_ambiguous"
      ],
      "dedupe": {
        "cluster_hint": "monongahela-power-allegheny-oil-spill-prevention-settlement-2001-11-13",
        "fingerprint": "monongahela_oil_spill_settlement_2001-11-13"
      }
    }
  ]
}